Metadata-Version: 2.4
Name: pywr
Version: 1.29.0
Summary: Python Water Resource model
Author-email: Joshua Arnott <josh@snorfalorpagus.net>, James Tomlinson <tomo.bbe@gmail.com>
Project-URL: Documentation, https://pywr.github.io/pywr/
Project-URL: Repository, https://github.com/pywr/pywr
Requires-Python: >=3.10
License-File: LICENSE.txt
Requires-Dist: pandas
Requires-Dist: networkx
Requires-Dist: numpy
Requires-Dist: scipy
Requires-Dist: tables
Requires-Dist: openpyxl
Requires-Dist: packaging
Provides-Extra: docs
Requires-Dist: sphinx; extra == "docs"
Requires-Dist: sphinx_rtd_theme; extra == "docs"
Requires-Dist: numpydoc; extra == "docs"
Requires-Dist: matplotlib; extra == "docs"
Provides-Extra: notebook
Requires-Dist: ipython; extra == "notebook"
Requires-Dist: jinja2; extra == "notebook"
Requires-Dist: matplotlib; extra == "notebook"
Provides-Extra: opt
Requires-Dist: platypus-opt; extra == "opt"
Requires-Dist: pygmo; extra == "opt"
Dynamic: license-file
